view_arc/__init__.py
view_arc/obstacle/__init__.py
view_arc/obstacle/api.py
view_arc/obstacle/clipping.py
view_arc/obstacle/debug.py
view_arc/obstacle/geometry.py
view_arc/obstacle/sweep.py
view_arc/obstacle/visualize.py
view_arc/tracking/__init__.py
view_arc/tracking/algorithm.py
view_arc/tracking/dataclasses.py
view_arc/tracking/validation.py
view_arc/tracking/visualize.py
actvalue_view_arc-0.1.1.dist-info/METADATA
actvalue_view_arc-0.1.1.dist-info/WHEEL
actvalue_view_arc-0.1.1.dist-info/licenses/LICENSE
actvalue_view_arc-0.1.1.dist-info/RECORD
