Metadata-Version: 2.4
Name: actvalue.view-arc
Version: 0.1.1
Summary: Track viewer attention on Areas of Interest (AOIs) over time by analyzing where viewers are looking during acquisition sessions.
Project-URL: Homepage, https://github.com/pmosconi/view-arc
Project-URL: Repository, https://github.com/pmosconi/view-arc.git
Project-URL: Issues, https://github.com/pmosconi/view-arc/issues
Project-URL: Documentation, https://github.com/pmosconi/view-arc#readme
Author-email: Paolo Mosconi <pmosconi@users.noreply.github.com>
License: MIT
License-File: LICENSE
Keywords: attention-tracking,computer-vision,obstacle-detection,view-arc
Classifier: Development Status :: 3 - Alpha
Classifier: Intended Audience :: Developers
Classifier: License :: OSI Approved :: MIT License
Classifier: Programming Language :: Python :: 3
Classifier: Programming Language :: Python :: 3.13
Classifier: Topic :: Scientific/Engineering :: Image Recognition
Requires-Python: >=3.13
Requires-Dist: numpy>=2.0.0
Provides-Extra: all
Requires-Dist: matplotlib>=3.9.0; extra == 'all'
Requires-Dist: opencv-python>=4.10.0; extra == 'all'
Requires-Dist: scikit-image>=0.24.0; extra == 'all'
Provides-Extra: dev
Requires-Dist: black>=24.0.0; extra == 'dev'
Requires-Dist: matplotlib>=3.9.0; extra == 'dev'
Requires-Dist: mypy>=1.11.0; extra == 'dev'
Requires-Dist: opencv-python-headless>=4.10.0; extra == 'dev'
Requires-Dist: pytest-cov>=4.1.0; extra == 'dev'
Requires-Dist: pytest>=8.0.0; extra == 'dev'
Requires-Dist: ruff>=0.6.0; extra == 'dev'
Requires-Dist: twine>=5.0.0; extra == 'dev'
Provides-Extra: examples
Requires-Dist: matplotlib>=3.9.0; extra == 'examples'
Requires-Dist: opencv-python>=4.10.0; extra == 'examples'
Requires-Dist: scikit-image>=0.24.0; extra == 'examples'
Provides-Extra: viz
Requires-Dist: matplotlib>=3.9.0; extra == 'viz'
Requires-Dist: opencv-python>=4.10.0; extra == 'viz'
